README.md
setup.py
marshmallow4k/__init__.py
marshmallow4k/marshmallow4k.py
marshmallow4k.egg-info/PKG-INFO
marshmallow4k.egg-info/SOURCES.txt
marshmallow4k.egg-info/dependency_links.txt
marshmallow4k.egg-info/top_level.txt