Metadata-Version: 2.1
Name: marshmallow4k
Version: 1.1
Summary: A package which allows you to create your own command-line interface. A parody of click and click-shell.
Author: marshmallow4k
